cloudmesh/vpn/__init__.py
cloudmesh/vpn/vpn.py
cloudmesh/vpn/windows.py
cloudmesh/vpn/bin/split-script-win.js
cloudmesh/vpn/bin/split-script-win.python.py
cloudmesh/vpn/command/__init__.py
cloudmesh/vpn/command/vpn.py
cloudmesh_vpn-5.0.16.dist-info/licenses/LICENSE
cloudmesh_vpn-5.0.16.dist-info/METADATA
cloudmesh_vpn-5.0.16.dist-info/WHEEL
cloudmesh_vpn-5.0.16.dist-info/top_level.txt
cloudmesh_vpn-5.0.16.dist-info/RECORD
